{"SolNode94":"Mercury|Apollodorus|MT_SURVIVAL|","SolNode130":"Mercury|Lares|MT_DEFENSE|","SolNode119":"Mercury|Caloris|MT_CAPTURE|","SolNode12":"Mercury|Elion|MT_MOBILE_DEFENSE|","SolNode103":"Mercury|Terminus|MT_EXTERMINATION|","SolNode28":"Mercury|M Prime|MT_SABOTAGE|","SolNode108":"Mercury|Tolstoj|MT_ASSASSINATION|","? - 0":"Mercury||MT_ASSASSINATION|","EventNode0":"Mercury|Balor|MT_SABOTAGE|","? - 1":"Mercury||MT_ASSASSINATION|","? - 2":"Mercury||MT_ASSASSINATION|","SolNode221":"Mercury|Neruda|MT_SABOTAGE|","SolNode222":"Mercury|Eminescu|MT_EXTERMINATION|","SolNode223":"Mercury|Boethius|MT_MOBILE_DEFENSE|","? - 3":"Mercury||MT_ASSASSINATION|","? - 4":"Mercury||MT_ASSASSINATION|","? - 5":"Mercury||MT_ASSASSINATION|","? - 6":"Mercury||MT_ASSASSINATION|","? - 7":"Mercury||MT_ASSASSINATION|","? - 8":"Mercury||MT_ASSASSINATION|","SolNode901":"Mercury|Caduceus|MT_EXTERMINATION|","? - 9":"Mercury||MT_ASSASSINATION|","SolNode224":"Mercury|Odin|MT_TERRITORY|","SolNode225":"Mercury|Suisei|MT_CAPTURE|","SolNode226":"Mercury|Pantheon|MT_EXTERMINATION|","SolNode227":"Mercury|Verdi|MT_COUNTER_INTEL|","? - 10":"Mercury||MT_ASSASSINATION|","? - 11":"Venus||MT_ASSASSINATION|","SolNode123":"Venus|V Prime|MT_RESCUE|","SolNode61":"Venus|Ishtar|MT_CAPTURE|","SolNode2":"Venus|Aphrodite|MT_CAPTURE|","SolNode71":"Venus|Vesper|MT_INTEL|","SolNode23":"Venus|Cytherean|MT_EXTERMINATION|","SolNode128":"Venus|E Gate|MT_EXCAVATE|","SolNode109":"Venus|Linea|MT_RESCUE|","? - 12":"Venus||MT_ASSASSINATION|","SolNode104":"Venus|Fossa|MT_ASSASSINATION|","PvpNode1":"Venus|Conclave|MT_PVP|","SolNode66":"Venus|Unda|MT_INTEL|","ClanNode1":"Venus|Malva|MT_EXCAVATE|","? - 13":"Venus||MT_ASSASSINATION|","? - 14":"Venus||MT_ASSASSINATION|","SolNode107":"Venus|Venera|MT_DEFENSE|","SolNode22":"Venus|Tessera|MT_SABOTAGE|","SolNode101":"Venus|Kiliken|MT_DEFENSE|","ClanNode0":"Venus|Romula|MT_DEFENSE|","? - 15":"Venus||MT_ASSASSINATION|","? - 16":"Venus||MT_ASSASSINATION|","? - 17":"Venus||MT_ASSASSINATION|","EventNode1":"Venus|Tethra|MT_SABOTAGE|","? - 18":"Venus||MT_ASSASSINATION|","? - 19":"Venus||MT_ASSASSINATION|","VenusHUB":"Venus|Vesper Relay|MT_PVP|","SolNode902":"Venus|Montes|MT_EXTERMINATION|","? - 20":"Earth||MT_ASSASSINATION|","SolNode63":"Earth|Mantle|MT_CAPTURE|","SolNode89":"Earth|Mariana|MT_SABOTAGE|","SolNode79":"Earth|Cambria|MT_EXCAVATE|","SolNode39":"Earth|Everest|MT_EXTERMINATION|","SolNode15":"Earth|Pacific|MT_CAPTURE|","SolNode26":"Earth|Lith|MT_DEFENSE|","? - 21":"Earth||MT_ASSASSINATION|","? - 22":"Earth||MT_ASSASSINATION|","SolNode27":"Earth|E Prime|MT_EXTERMINATION|","SolNode85":"Earth|Gaia|MT_TERRITORY|","SolNode59":"Earth|Eurasia|MT_EXTERMINATION|","SolNode75":"Earth|Lua|MT_DEFENSE|","? - 23":"Earth||MT_ASSASSINATION|","EarthHUB":"Earth|Strata Relay|MT_PVP|","SolNode24":"Earth|Oro|MT_SABOTAGE|","EventNode2":"Earth|Gate Crash|MT_SABOTAGE|","ClanNode2":"Earth|Coba|MT_DEFENSE|","SolNode903":"Earth|Erpo|MT_TERRITORY|","? - 24":"Earth||MT_ASSASSINATION|","? - 25":"Earth||MT_ASSASSINATION|","ClanNode3":"Earth|Tikal|MT_EXCAVATE|","? - 26":"Earth||MT_ASSASSINATION|","? - 27":"Earth||MT_ASSASSINATION|","? - 28":"Earth||MT_ASSASSINATION|","? - 29":"Earth||MT_ASSASSINATION|","? - 30":"Earth||MT_ASSASSINATION|","SolNode35":"Mars|Arcadia|MT_SURVIVAL|","? - 31":"Mars||MT_ASSASSINATION|","? - 32":"Mars||MT_ASSASSINATION|","SolNode11":"Mars|Tharsis|MT_SABOTAGE|","SolNode113":"Mars|Ares|MT_CAPTURE|","SolNode30":"Mars|Olympus|MT_DEFENSE|","? - 33":"Mars||MT_ASSASSINATION|","SolNode68":"Mars|Vallis|MT_RESCUE|","SolNode58":"Mars|Hellas|MT_MOBILE_DEFENSE|","SolNode106":"Mars|Alator|MT_CAPTURE|","SolNode41":"Mars|Arval|MT_EXTERMINATION|","SolNode14":"Mars|Ultor|MT_EXTERMINATION|","SolNode16":"Mars|Augustus|MT_TERRITORY|","? - 34":"Mars||MT_ASSASSINATION|","SolNode45":"Mars|Ara|MT_SURVIVAL|","? - 35":"Mars||MT_ASSASSINATION|","? - 36":"Mars||MT_ASSASSINATION|","SolNode54":"Mars|Silvanus|MT_EXTERMINATION|","SolNode36":"Mars|Martialis|MT_INTEL|","ClanNode8":"Mars|Kadesh|MT_DEFENSE|","MarsHUB":"Mars|Shaun's Relay Test|MT_PVP|","SolNode99":"Mars|War|MT_ASSASSINATION|","EventNode3":"Mars|Elatha|MT_DEFENSE|","SolNode65":"Mars|Gradivus|MT_SABOTAGE|","ClanNode9":"Mars|Wahiba|MT_SURVIVAL|","SolNode115":"Mars|Quirinus|MT_CAPTURE|","SolNode46":"Mars|Spear|MT_RESCUE|","SolNode904":"Mars|Syrtis|MT_EXTERMINATION|","? - 37":"Mars||MT_ASSASSINATION|","? - 38":"Mars||MT_ASSASSINATION|","? - 39":"Mars||MT_ASSASSINATION|","? - 40":"Mars||MT_ASSASSINATION|","? - 41":"Mars||MT_ASSASSINATION|","? - 42":"Mars||MT_ASSASSINATION|","? - 43":"Mars||MT_ASSASSINATION|","? - 44":"Mars||MT_ASSASSINATION|","SolNode87":"Jupiter|Ganymede|MT_EXTERMINATION|","SolNode88":"Jupiter|Adrastea|MT_EXTERMINATION|","? - 45":"Jupiter||MT_ASSASSINATION|","SolNode97":"Jupiter|Amalthea|MT_SABOTAGE|","SolNode126":"Jupiter|Metis|MT_CAPTURE|","? - 46":"Jupiter||MT_ASSASSINATION|","SolNode125":"Jupiter|Io|MT_DEFENSE|","SolNode100":"Jupiter|Elara|MT_SURVIVAL|","SolNode10":"Jupiter|Thebe|MT_COUNTER_INTEL|","PvpNode8":"Jupiter|Conclave|MT_PVP|","SolNode25":"Jupiter|Callisto|MT_TERRITORY|","SolNode121":"Jupiter|Carpo|MT_EXTERMINATION|","SolNode53":"Jupiter|Themisto|MT_ASSASSINATION|","SolNode74":"Jupiter|Carme|MT_MOBILE_DEFENSE|","? - 47":"Jupiter||MT_ASSASSINATION|","ClanNode4":"Jupiter|Sinai|MT_DEFENSE|","EventNode4":"Jupiter|Bres|MT_SABOTAGE|","SolNode73":"Jupiter|Ananke|MT_CAPTURE|","? - 48":"Jupiter||MT_ASSASSINATION|","? - 49":"Jupiter||MT_ASSASSINATION|","? - 50":"Jupiter||MT_ASSASSINATION|","SolNode905":"Jupiter|Galilea|MT_SABOTAGE|","ClanNode5":"Jupiter|Cameria|MT_SURVIVAL|","? - 51":"Jupiter||MT_ASSASSINATION|","? - 52":"Jupiter||MT_ASSASSINATION|","? - 53":"Jupiter||MT_ASSASSINATION|","? - 54":"Jupiter||MT_ASSASSINATION|","SolNode110":"Saturn|Hyperion|MT_EXTERMINATION|","SolNode7":"Saturn|Epimetheus|MT_COUNTER_INTEL|","? - 55":"Saturn||MT_ASSASSINATION|","SolNode42":"Saturn|Helene|MT_DEFENSE|","? - 56":"Saturn||MT_ASSASSINATION|","SolNode19":"Saturn|Enceladus|MT_CAPTURE|","SolNode96":"Saturn|Titan|MT_SABOTAGE|","? - 57":"Saturn||MT_ASSASSINATION|","SolNode67":"Saturn|Dione|MT_SABOTAGE|","? - 58":"Saturn||MT_ASSASSINATION|","SolNode44":"Saturn|Mimas|MT_SURVIVAL|","SolNode91":"Saturn|Iapetus|MT_TERRITORY|","SolNode47":"Saturn|Janus|MT_EXTERMINATION|","SolNode93":"Saturn|Keeler|MT_SURVIVAL|","SolNode32":"Saturn|Tethys|MT_ASSASSINATION|","? - 59":"Saturn||MT_ASSASSINATION|","SolNode80":"Saturn|Phoebe|MT_CAPTURE|","SolNode18":"Saturn|Rhea|MT_SABOTAGE|","? - 60":"Saturn||MT_ASSASSINATION|","SolNode37":"Saturn|Pallene|MT_SABOTAGE|","SolNode20":"Saturn|Telesto|MT_EXTERMINATION|","SolNode86":"Saturn|Aegaeon|MT_EXTERMINATION|","SolNode55":"Saturn|Methone|MT_COUNTER_INTEL|","SolNode70":"Saturn|Cassini|MT_SURVIVAL|","SolNode31":"Saturn|Anthe|MT_RESCUE|","? - 61":"Saturn||MT_ASSASSINATION|","SolNode50":"Saturn|Numa|MT_RESCUE|","? - 62":"Saturn||MT_ASSASSINATION|","SolNode82":"Saturn|Calypso|MT_CAPTURE|","SolNode906":"Saturn|Pandora|MT_EXTERMINATION|","? - 63":"Saturn||MT_ASSASSINATION|","EventNode5":"Saturn|Birog|MT_DEFENSE|","PvpNode0":"Saturn|Conclave|MT_PVP|","ClanNode13":"Saturn|Piscinas|MT_SURVIVAL|","? - 64":"Saturn||MT_ASSASSINATION|","ClanNode12":"Saturn|Caracol|MT_DEFENSE|","SolNode29":"Uranus|Oberon|MT_EXTERMINATION|","SolNode33":"Uranus|Ariel|MT_SABOTAGE|","? - 65":"Uranus||MT_ASSASSINATION|","SolNode105":"Uranus|Titania|MT_ASSASSINATION|","SolNode64":"Uranus|Umbriel|MT_INTEL|","SolNode3":"Uranus|Cordelia|MT_EXTERMINATION|","? - 66":"Uranus||MT_ASSASSINATION|","SolNode90":"Uranus|Miranda|MT_DEFENSE|","SolNode69":"Uranus|Ophelia|MT_SURVIVAL|","SolNode52":"Uranus|Portia|MT_SABOTAGE|","SolNode83":"Uranus|Cressida|MT_SURVIVAL|","SolNode111":"Uranus|Juliet|MT_COUNTER_INTEL|","SolNode98":"Uranus|Desdemona|MT_CAPTURE|","SolNode77":"Uranus|Cupid|MT_SURVIVAL|","SolNode9":"Uranus|Rosalind|MT_INTEL|","? - 67":"Uranus||MT_ASSASSINATION|","SolNode13":"Uranus|Bianca|MT_DEFENSE|","? - 68":"Uranus||MT_ASSASSINATION|","? - 69":"Uranus||MT_ASSASSINATION|","SolNode40":"Uranus|Prospero|MT_SABOTAGE|","SolNode5":"Uranus|Perdita|MT_COUNTER_INTEL|","SolNode116":"Uranus|Mab|MT_RESCUE|","SolNode112":"Uranus|Setebos|MT_SABOTAGE|","SolNode60":"Uranus|Caliban|MT_RESCUE|","? - 70":"Uranus||MT_ASSASSINATION|","SolNode114":"Uranus|Puck|MT_EXTERMINATION|","? - 71":"Uranus||MT_ASSASSINATION|","? - 72":"Uranus||MT_ASSASSINATION|","ClanNode16":"Uranus|Ur|MT_DEFENSE|","SolNode34":"Uranus|Sycorax|MT_EXTERMINATION|","SolNode122":"Uranus|Stephano|MT_TERRITORY|","SolNode124":"Uranus|Trinculo|MT_CAPTURE|","SolNode907":"Uranus|Caelus|MT_TERRITORY|","? - 73":"Uranus||MT_ASSASSINATION|","ClanNode17":"Uranus|Assur|MT_SURVIVAL|","EventNode6":"Uranus|Ethniu|MT_SURVIVAL|","SolNode49":"Neptune|Larissa|MT_MOBILE_DEFENSE|","SolNode95":"Neptune|Thalassa|MT_RESCUE|","SolNode117":"Neptune|Naiad|MT_COUNTER_INTEL|","SolNode1":"Neptune|Galatea|MT_CAPTURE|","? - 74":"Neptune||MT_ASSASSINATION|","? - 75":"Neptune||MT_ASSASSINATION|","SolNode17":"Neptune|Proteus|MT_DEFENSE|","SolNode78":"Neptune|Triton|MT_EXCAVATE|","SolNode6":"Neptune|Despina|MT_DEFENSE|","SolNode57":"Neptune|Sao|MT_COUNTER_INTEL|","SolNode120":"Neptune|Halimede|MT_SABOTAGE|","? - 76":"Neptune||MT_ASSASSINATION|","SolNode62":"Neptune|Neso|MT_EXTERMINATION|","SolNode908":"Neptune|Salacia|MT_SABOTAGE|","SolNode127":"Neptune|Psamathe|MT_ASSASSINATION|","SolNode118":"Neptune|Laomedeia|MT_INTEL|","? - 77":"Neptune||MT_ASSASSINATION|","SolNode84":"Neptune|Nereid|MT_RESCUE|","ClanNode20":"Neptune|Yursa|MT_DEFENSE|","ClanNode21":"Neptune|Kelashin|MT_SURVIVAL|","? - 78":"Neptune||MT_ASSASSINATION|","? - 79":"Neptune||MT_ASSASSINATION|","EventNode7":"Neptune|Buarainech|MT_SABOTAGE|","PvpNode3":"Neptune|Conclave|MT_PVP|","? - 80":"Neptune||MT_ASSASSINATION|","? - 81":"Neptune||MT_ASSASSINATION|","? - 82":"Neptune||MT_ASSASSINATION|","SolNode4":"Pluto|Acheron|MT_EXTERMINATION|","SolNode72":"Pluto|Outer Terminus|MT_DEFENSE|","? - 83":"Pluto||MT_ASSASSINATION|","SolNode48":"Pluto|Regna|MT_RESCUE|","SolNode21":"Pluto|Narcissus|MT_DEFENSE|","SolNode92":"Pluto|Charon|MT_SABOTAGE|","SolNode76":"Pluto|Hydra|MT_CAPTURE|","SolNode51":"Pluto|Hades|MT_ASSASSINATION|","SolNode38":"Pluto|Minthe|MT_MOBILE_DEFENSE|","? - 84":"Pluto||MT_ASSASSINATION|","SolNode8":"Pluto|Nix|MT_COUNTER_INTEL|","SolNode56":"Pluto|Cypress|MT_SABOTAGE|","SolNode43":"Pluto|Cerberus|MT_TERRITORY|","SolNode81":"Pluto|Palus|MT_SURVIVAL|","ClanNode24":"Pluto|Sechura|MT_DEFENSE|","? - 85":"Pluto||MT_ASSASSINATION|","SolNode102":"Pluto|Oceanum|MT_INTEL|","PvpNode6":"Pluto|Conclave|MT_PVP|","? - 86":"Pluto||MT_ASSASSINATION|","ClanNode25":"Pluto|Hieracon|MT_SURVIVAL|","? - 87":"Pluto||MT_ASSASSINATION|","? - 88":"Pluto||MT_ASSASSINATION|","? - 89":"Pluto||MT_ASSASSINATION|","EventNode8":"Pluto|Corb|MT_CAPTURE|","? - 90":"Pluto||MT_ASSASSINATION|","? - 91":"Pluto||MT_ASSASSINATION|","? - 92":"Pluto||MT_ASSASSINATION|","SolNode136":"Ceres|Olla|MT_RESCUE|","? - 93":"Ceres||MT_ASSASSINATION|","SolNode131":"Ceres|Pallas|MT_SABOTAGE|","SolNode133":"Ceres|Vedic|MT_EXTERMINATION|","SolNode135":"Ceres|Thon|MT_SABOTAGE|","? - 94":"Ceres||MT_ASSASSINATION|","? - 95":"Ceres||MT_ASSASSINATION|","SolNode132":"Ceres|Bode|MT_CAPTURE|","SolNode134":"Ceres|Varro|MT_DEFENSE|","SolNode139":"Ceres|Lex|MT_INTEL|","SolNode141":"Ceres|Ker|MT_COUNTER_INTEL|","SolNode137":"Ceres|Nuovo|MT_SURVIVAL|","SolNode142":"Ceres|Hapke|MT_CAPTURE|","SolNode140":"Ceres|Kiste|MT_MOBILE_DEFENSE|","? - 96":"Ceres||MT_ASSASSINATION|","SolNode138":"Ceres|Ludi|MT_EXTERMINATION|","SolNode143":"Ceres|Gefion|MT_RETRIEVAL|","SolNode144":"Ceres|Exta|MT_ASSASSINATION|","SolNode149":"Ceres|Casta|MT_DEFENSE|","? - 97":"Ceres||MT_ASSASSINATION|","? - 98":"Ceres||MT_ASSASSINATION|","SolNode148":"Ceres|Cerium|MT_RETRIEVAL|","SolNode147":"Ceres|Cinxia|MT_RESCUE|","SolNode150":"Ceres|Albedo|MT_COUNTER_INTEL|","SolNode145":"Ceres|Egeria|MT_SURVIVAL|","? - 99":"Ceres||MT_ASSASSINATION|","SolNode146":"Ceres|Draco|MT_TERRITORY|","? - 100":"Ceres||MT_ASSASSINATION|","? - 101":"Ceres||MT_ASSASSINATION|","? - 102":"Ceres||MT_ASSASSINATION|","? - 103":"Ceres||MT_ASSASSINATION|","EventNode9":"Ceres|Gate Crash|MT_SABOTAGE|","? - 104":"Ceres||MT_ASSASSINATION|","ClanNode23":"Ceres|Gabii|MT_SURVIVAL|","? - 105":"Ceres||MT_ASSASSINATION|","ClanNode22":"Ceres|Seimeni|MT_DEFENSE|","SolNode156":"Eris|Cyath|MT_MOBILE_DEFENSE|","SolNode155":"Eris|Cosis|MT_CAPTURE|","SolNode154":"Eris|Candiru|MT_HIVE|","SolNode152":"Eris|Ascar|MT_MOBILE_DEFENSE|","? - 106":"Eris||MT_ASSASSINATION|","SolNode157":"Eris|Giardia|MT_MOBILE_DEFENSE|","? - 107":"Eris||MT_ASSASSINATION|","SolNode151":"Eris|Acanth|MT_EXTERMINATION|","SolNode153":"Eris|Brugia|MT_RESCUE|","SolNode159":"Eris|Lepis|MT_HIVE|","SolNode164":"Eris|Kala-azar|MT_DEFENSE|","SolNode161":"Eris|Hymeno|MT_SURVIVAL|","SolNode162":"Eris|Isos|MT_CAPTURE|","? - 108":"Eris||MT_ASSASSINATION|","SolNode158":"Eris|Gnathos|MT_DEFENSE|","SolNode160":"Eris|Histo|MT_EXTERMINATION|","SolNode165":"Eris|Naeglar|MT_EXTERMINATION|","SolNode163":"Eris|Ixodes|MT_DEFENSE|","? - 109":"Eris||MT_ASSASSINATION|","SolNode171":"Eris|Saxis|MT_EXTERMINATION|","SolNode168":"Eris|Phalan|MT_SURVIVAL|","? - 110":"Eris||MT_ASSASSINATION|","SolNode167":"Eris|Oestrus|MT_MOBILE_DEFENSE|","SolNode170":"Eris|Ranova|MT_RESCUE|","SolNode169":"Eris|Psoro|MT_HIVE|","SolNode166":"Eris|Nimus|MT_SURVIVAL|","? - 111":"Eris||MT_ASSASSINATION|","EventNode10":"Eris|Lugh|MT_COUNTER_INTEL|","SolNode173":"Eris|Solium|MT_MOBILE_DEFENSE|","ClanNode18":"Eris|Akkad|MT_DEFENSE|","SolNode174":"Eris|Sparga|MT_RESCUE|","SolNode172":"Eris|Xini|MT_DEFENSE|","SolNode176":"Eris|Viver|MT_HIVE|","ClanNode19":"Eris|Zabala|MT_SURVIVAL|","SolNode175":"Eris|Sporid|MT_HIVE|","PvpNode4":"Eris|Conclave|MT_PVP|","SolNode177":"Sedna|Kappa|MT_MOBILE_DEFENSE|","SolNode184":"Sedna|Rusalka|MT_COUNTER_INTEL|","SolNode182":"Sedna|Camenae|MT_DEFENSE|","SolNode181":"Sedna|Adaro|MT_EXTERMINATION|","SolNode183":"Sedna|Vodyanoi|MT_MOBILE_DEFENSE|","SolNode178":"Sedna|Hyosube|MT_SABOTAGE|","SolNode180":"Sedna|Undine|MT_SABOTAGE|","SolNode179":"Sedna|Jengu|MT_RESCUE|","? - 112":"Sedna||MT_ASSASSINATION|","SolNode190":"Sedna|Nakki|MT_SABOTAGE|","SolNode185":"Sedna|Berehynia|MT_TERRITORY|","SolNode192":"Sedna|Tikoloshe|MT_INTEL|","? - 113":"Sedna||MT_ASSASSINATION|","SolNode187":"Sedna|Selkie|MT_SURVIVAL|","SolNode191":"Sedna|Marid|MT_EXTERMINATION|","SolNode186":"Sedna|Phithale|MT_SABOTAGE|","SolNode188":"Sedna|Kelpie|MT_SABOTAGE|","SolNode189":"Sedna|Naga|MT_RESCUE|","? - 114":"Sedna||MT_ASSASSINATION|","? - 115":"Sedna||MT_ASSASSINATION|","SolNode199":"Sedna|Yam|MT_SABOTAGE|","SolNode194":"Sedna|Ponaturi|MT_COUNTER_INTEL|","SolNode193":"Sedna|Merrow|MT_ASSASSINATION|","SolNode196":"Sedna|Charybdis|MT_COUNTER_INTEL|","SolNode197":"Sedna|Graeae|MT_MOBILE_DEFENSE|","SolNode195":"Sedna|Hydron|MT_DEFENSE|","SolNode198":"Sedna|Scylla|MT_INTEL|","EventNode11":"Sedna|Nemed|MT_INTEL|","? - 116":"Sedna||MT_ASSASSINATION|","SolNode201":"Sedna|Tiamat|MT_CAPTURE|","SolNode202":"Sedna|Yemaja|MT_SURVIVAL|","PvpNode7":"Sedna|Conclave|MT_PVP|","? - 117":"Sedna||MT_ASSASSINATION|","ClanNode14":"Sedna|Amarna|MT_SURVIVAL|","SolNode200":"Sedna|Veles|MT_RESCUE|","ClanNode15":"Sedna|Sangeru|MT_DEFENSE|","SolNode203":"Europa|Abaddon|MT_CAPTURE|","SolNode207":"Europa|Gamygyn|MT_INTEL|","SolNode204":"Europa|Armaros|MT_TERRITORY|","SolNode209":"Europa|Morax|MT_INTEL|","SolNode206":"Europa|Eligor|MT_DEFENSE|","SolNode208":"Europa|Lillith|MT_EXCAVATE|","SolNode210":"Europa|Naamah|MT_ASSASSINATION|","? - 118":"Europa||MT_ASSASSINATION|","SolNode205":"Europa|Baal|MT_MOBILE_DEFENSE|","? - 119":"Europa||MT_ASSASSINATION|","SolNode216":"Europa|Valefor|MT_DEFENSE|","? - 120":"Europa||MT_ASSASSINATION|","EventNode16":"Europa|Cryotic Front|MT_CAPTURE|","SolNode214":"Europa|Sorath|MT_MOBILE_DEFENSE|","SolNode211":"Europa|Ose|MT_EXCAVATE|","SolNode215":"Europa|Valac|MT_INTEL|","SolNode213":"Europa|Shax|MT_RESCUE|","SolNode212":"Europa|Paimon|MT_DEFENSE|","PvpNode5":"Europa|Conclave|MT_PVP|","SolNode217":"Europa|Orias|MT_RESCUE|","SolNode218":"Europa|Zagan|MT_CAPTURE|","ClanNode6":"Europa|Larzac|MT_DEFENSE|","EventNode15":"Europa|Cryotic Front|MT_CAPTURE|","SolNode219":"Europa|Beleth|MT_CAPTURE|","SolNode220":"Europa|Kokabiel|MT_SABOTAGE|","EventNode12":"Europa|Cryotic Front|MT_EXCAVATE|","? - 121":"Europa||MT_ASSASSINATION|","? - 122":"Europa||MT_ASSASSINATION|","? - 123":"Europa||MT_ASSASSINATION|","? - 124":"Europa||MT_ASSASSINATION|","? - 125":"Europa||MT_ASSASSINATION|","? - 126":"Europa||MT_ASSASSINATION|","EventNode17":"Europa|Cryotic Front|MT_CAPTURE|","ClanNode7":"Europa|Cholistan|MT_EXCAVATE|","? - 127":"Europa||MT_ASSASSINATION|","? - 128":"Europa||MT_ASSASSINATION|","SettlementNode6":"Phobos|Limtoc|MT_CAPTURE|","PvpNode2":"Phobos|Conclave|MT_PVP|","SettlementNode1":"Phobos|Roche|MT_EXTERMINATION|","? - 129":"Phobos||MT_ASSASSINATION|","SettlementNode7":"Phobos|Hall|MT_MOBILE_DEFENSE|","SettlementNode5":"Phobos|Grildrig|MT_RESCUE|","SettlementNode3":"Phobos|Stickney|MT_EXCAVATE|","SettlementNode2":"Phobos|Skyresh|MT_COUNTER_INTEL|","SettlementNode4":"Phobos|Drunlo|MT_DEFENSE|","SettlementNode13":"Phobos|D'Arrest|MT_SABOTAGE|","SettlementNode12":"Phobos|Monolith|MT_RESCUE|","SettlementNode10":"Phobos|Kepler|MT_DEFENSE|","SettlementNode15":"Phobos|Sharpless|MT_MOBILE_DEFENSE|","? - 130":"Phobos||MT_ASSASSINATION|","SettlementNode8":"Phobos|Reldresal|MT_SABOTAGE|","SettlementNode11":"Phobos|Gulliver|MT_RESCUE|","SettlementNode14":"Phobos|Shklovsky|MT_INTEL|","SettlementNode9":"Phobos|Clustril|MT_EXTERMINATION|","SettlementNode16":"Phobos|Wendell|MT_EXCAVATE|","SettlementNode19":"Phobos|Todd|MT_CAPTURE|","EventNode13":"Phobos|Shifting Sands|MT_SABOTAGE|","SettlementNode17":"Phobos|Flimnap|MT_COUNTER_INTEL|","ClanNode10":"Phobos|Memphis|MT_DEFENSE|","SettlementNode20":"Phobos|Iliad|MT_ASSASSINATION|","? - 131":"Phobos||MT_ASSASSINATION|","EventNode14":"Phobos|Gate Crash|MT_SABOTAGE|","SettlementNode18":"Phobos|Opik|MT_TERRITORY|","? - 132":"Phobos||MT_ASSASSINATION|","? - 133":"Phobos||MT_ASSASSINATION|","? - 134":"Phobos||MT_ASSASSINATION|","? - 135":"Phobos||MT_ASSASSINATION|","? - 136":"Phobos||MT_ASSASSINATION|","? - 137":"Phobos||MT_ASSASSINATION|","? - 138":"Phobos||MT_ASSASSINATION|","? - 139":"Phobos||MT_ASSASSINATION|","ClanNode11":"Phobos|Zeugma|MT_EXCAVATE|"}