{"SolNode94":"수성|Apollodorus|Survival|Grineer|5 - 10|20 - 50|0.2|0",
"SolNode130":"수성|Lares|Defense|Grineer|5 - 10|20 - 50|0.2|0",
"SolNode119":"수성|Caloris|Capture|Grineer|4 - 5|20 - 50|0.2|0",
"SolNode12":"수성|Elion|Mobile Defense|Grineer|4 - 5|20 - 50|0.2|0",
"SolNode103":"수성|Terminus|Extermination|Grineer|3 - 4|20 - 50|0.2|0",
"SolNode28":"수성|M Prime|Sabotage|Grineer|3 - 4|20 - 50|0.2|0",
"SolNode108":"수성|Tolstoj|Assassination|Grineer|3 - 4|20 - 50|0.2|0",
"? - 0":"수성||Assassination|Grineer|1 - 1|20 - 50|0.2|0",
"EventNode0":"수성|Balor|Sabotage|Grineer|1 - 1|20 - 50|0.2|0",
"? - 1":"수성||Assassination|Grineer|1 - 1|20 - 50|0.2|1",
"? - 2":"수성||Assassination|Grineer|1 - 1|20 - 50|0.2|1",
"SolNode221":"수성|Neruda|Sabotage|Grineer|5 - 6|20 - 50|0.2|1",
"SolNode222":"수성|Eminescu|Extermination|Grineer|5 - 6|20 - 50|0.2|1",
"SolNode223":"수성|Boethius|Mobile Defense|Grineer|6 - 7|20 - 50|0.2|1",
"? - 3":"수성||Assassination|Grineer|1 - 1|20 - 50|0.2|1",
"? - 4":"수성||Assassination|Grineer|1 - 1|20 - 50|0.2|1",
"? - 5":"수성||Assassination|Grineer|1 - 1|20 - 50|0.2|1",
"? - 6":"수성||Assassination|Grineer|1 - 1|20 - 50|0.2|1",
"? - 7":"수성||Assassination|Grineer|1 - 1|20 - 50|0.2|2",
"? - 8":"수성||Assassination|Grineer|1 - 1|20 - 50|0.2|2",
"? - 9":"수성||Assassination|Grineer|1 - 1|20 - 50|0.2|2",
"? - 10":"수성||Assassination|Grineer|1 - 1|20 - 50|0.2|2",
"SolNode224":"수성|Odin|Interception|Grineer|7 - 8|20 - 50|0.2|2",
"SolNode225":"수성|Suisei|Capture|Grineer|7 - 8|20 - 50|0.2|2",
"SolNode226":"수성|Pantheon|Extermination|Grineer|8 - 9|20 - 50|0.2|2",
"SolNode227":"수성|Verdi|Deception|Grineer|8 - 9|20 - 50|0.2|2",
"? - 11":"수성||Assassination|Grineer|1 - 1|20 - 50|0.2|2",
"? - 12":"금성||Assassination|Grineer|1 - 1|20 - 40|0.2|0",
"SolNode123":"금성|V Prime|Rescue|Corpus|8 - 9|20 - 40|0.2|0",
"SolNode61":"금성|Ishtar|Capture|Corpus|8 - 9|20 - 40|0.2|0",
"SolNode2":"금성|Aphrodite|Capture|Corpus|9 - 10|20 - 40|0.2|0",
"SolNode71":"금성|Vesper|Spy|Corpus|9 - 10|20 - 40|0.2|0",
"SolNode23":"금성|Cytherean|Extermination|Corpus|9 - 10|20 - 40|0.2|0",
"SolNode128":"금성|E Gate|Survival|Corpus|9 - 14|20 - 40|0.2|0",
"SolNode109":"금성|Linea|Rescue|Corpus|10 - 11|20 - 40|0.2|0",
"? - 13":"금성||Assassination|Grineer|1 - 1|20 - 40|0.2|0",
"SolNode104":"금성|Fossa|Assassination|Corpus|11 - 12|20 - 40|0.2|1",
"PvpNode1":"금성|Conclave|MT_PVP|Corrupted|0 - 100|20 - 40|0.2|1",
"SolNode66":"금성|Unda|Spy|Corpus|10 - 11|20 - 40|0.2|1",
"ClanNode1":"금성|Malva|Survival|Infestation|12 - 22|20 - 40|0.2|1",
"? - 14":"금성||Assassination|Grineer|1 - 1|20 - 40|0.2|1",
"? - 15":"금성||Assassination|Grineer|1 - 1|20 - 40|0.2|1",
"SolNode107":"금성|Venera|Defense|Corpus|10 - 15|20 - 40|0.2|1",
"SolNode22":"금성|Tessera|Sabotage|Corpus|10 - 11|20 - 40|0.2|1",
"SolNode101":"금성|Kiliken|Defense|Corpus|10 - 15|20 - 40|0.2|1",
"ClanNode0":"금성|Romula|Defense|Infestation|12 - 22|20 - 40|0.2|2",
"? - 16":"금성||Assassination|Grineer|1 - 1|20 - 40|0.2|2",
"? - 17":"금성||Assassination|Grineer|1 - 1|20 - 40|0.2|2",
"? - 18":"금성||Assassination|Grineer|1 - 1|20 - 40|0.2|2",
"EventNode1":"금성|Tethra|Sabotage|Grineer|3 - 3|20 - 40|0.2|2",
"? - 19":"금성||Assassination|Grineer|1 - 1|20 - 40|0.2|2",
"? - 20":"금성||Assassination|Grineer|1 - 1|20 - 40|0.2|2",
"Venus_HUB":"금성|Vesper Relay|MT_PVP|Corrupted|3 - 3|20 - 40|0.2|2",
"? - 21":"금성||Assassination|Grineer|1 - 1|20 - 40|0.2|2",
"? - 22":"지구||Assassination|Grineer|1 - 1|10 - 50|0.30000001|0",
"SolNode63":"지구|Mantle|Capture|Grineer|7 - 8|10 - 50|0.30000001|0",
"SolNode89":"지구|Mariana|Sabotage|Grineer|8 - 9|10 - 50|0.30000001|0",
"SolNode79":"지구|Cambria|Survival|Grineer|8 - 11|10 - 50|0.30000001|0",
"SolNode39":"지구|Everest|Extermination|Grineer|8 - 9|10 - 50|0.30000001|0",
"SolNode15":"지구|Pacific|Capture|Grineer|7 - 8|10 - 50|0.30000001|0",
"SolNode26":"지구|Lith|Defense|Grineer|7 - 10|10 - 50|0.30000001|0",
"? - 23":"지구||Assassination|Grineer|1 - 1|10 - 50|0.30000001|0",
"? - 24":"지구||Assassination|Grineer|1 - 1|10 - 50|0.30000001|0",
"SolNode27":"지구|E Prime|Extermination|Grineer|6 - 7|10 - 50|0.30000001|1",
"SolNode85":"지구|Gaia|Interception|Grineer|6 - 7|10 - 50|0.30000001|1",
"SolNode59":"지구|Eurasia|Extermination|Grineer|7 - 8|10 - 50|0.30000001|1",
"SolNode75":"지구|Lua|Defense|Grineer|6 - 8|10 - 50|0.30000001|1",
"? - 25":"지구||Assassination|Grineer|1 - 1|10 - 50|0.30000001|1",
"Earth_HUB":"지구|Strata Relay|MT_PVP|Corrupted|6 - 6|10 - 50|0.30000001|1",
"SolNode24":"지구|Oro|Sabotage|Grineer|6 - 7|10 - 50|0.30000001|1",
"EventNode2":"지구|Tethra's Doom|Sabotage|Grineer|6 - 6|10 - 50|0.30000001|1",
"ClanNode2":"지구|Coba|Defense|Infestation|11 - 21|10 - 50|0.30000001|1",
"? - 26":"지구||Assassination|Grineer|1 - 1|10 - 50|0.30000001|2",
"? - 27":"지구||Assassination|Grineer|1 - 1|10 - 50|0.30000001|2",
"? - 28":"지구||Assassination|Grineer|1 - 1|10 - 50|0.30000001|2",
"ClanNode3":"지구|Tikal|Survival|Infestation|11 - 21|10 - 50|0.30000001|2",
"? - 29":"지구||Assassination|Grineer|1 - 1|10 - 50|0.30000001|2",
"? - 30":"지구||Assassination|Grineer|1 - 1|10 - 50|0.30000001|2",
"? - 31":"지구||Assassination|Grineer|1 - 1|10 - 50|0.30000001|2",
"? - 32":"지구||Assassination|Grineer|1 - 1|10 - 50|0.30000001|2",
"? - 33":"지구||Assassination|Grineer|1 - 1|10 - 50|0.30000001|2",
"SolNode35":"화성|Arcadia|Survival|Corpus|11 - 12|20 - 50|0.30000001|0",
"? - 34":"화성||Assassination|Grineer|1 - 1|20 - 50|0.30000001|0",
"? - 35":"화성||Assassination|Grineer|1 - 1|20 - 50|0.30000001|0",
"SolNode11":"화성|Tharsis|Sabotage|Corpus|10 - 11|20 - 50|0.30000001|0",
"SolNode113":"화성|Ares|Capture|Corpus|10 - 11|20 - 50|0.30000001|0",
"SolNode30":"화성|Olympus|Defense|Corpus|12 - 17|20 - 50|0.30000001|0",
"? - 36":"화성||Assassination|Grineer|1 - 1|20 - 50|0.30000001|0",
"SolNode68":"화성|Vallis|Rescue|Corpus|11 - 12|20 - 50|0.30000001|0",
"SolNode58":"화성|Hellas|Mobile Defense|Corpus|11 - 12|20 - 50|0.30000001|0",
"SolNode106":"화성|Alator|Capture|Corpus|10 - 11|20 - 50|0.30000001|1",
"SolNode41":"화성|Arval|Extermination|Corpus|11 - 12|20 - 50|0.30000001|1",
"SolNode14":"화성|Ultor|Extermination|Corpus|10 - 11|20 - 50|0.30000001|1",
"SolNode16":"화성|Augustus|Interception|Corpus|12 - 13|20 - 50|0.30000001|1",
"? - 37":"화성||Assassination|Grineer|1 - 1|20 - 50|0.30000001|1",
"SolNode45":"화성|Ara|Survival|Corpus|11 - 16|20 - 50|0.30000001|1",
"? - 38":"화성||Assassination|Grineer|1 - 1|20 - 50|0.30000001|1",
"? - 39":"화성||Assassination|Grineer|1 - 1|20 - 50|0.30000001|1",
"SolNode54":"화성|Silvanus|Extermination|Corpus|11 - 12|20 - 50|0.30000001|1",
"SolNode36":"화성|Martialis|Spy|Corpus|10 - 11|20 - 50|0.30000001|2",
"ClanNode8":"화성|Kadesh|Defense|Infestation|14 - 24|20 - 50|0.30000001|2",
"? - 40":"화성||Assassination|Grineer|1 - 1|20 - 50|0.30000001|2",
"SolNode99":"화성|War|Assassination|Corpus|12 - 13|20 - 50|0.30000001|2",
"EventNode3":"화성|Elatha|Defense|Corpus|9 - 9|20 - 50|0.30000001|2",
"SolNode65":"화성|Gradivus|Sabotage|Corpus|9 - 10|20 - 50|0.30000001|2",
"ClanNode9":"화성|Wahiba|Survival|Infestation|14 - 24|20 - 50|0.30000001|2",
"SolNode115":"화성|Quirinus|Capture|Corpus|9 - 10|20 - 50|0.30000001|2",
"SolNode46":"화성|Spear|Rescue|Corpus|9 - 10|20 - 50|0.30000001|2",
"SolNode87":"목성|Ganymede|Extermination|Corpus|11 - 12|20 - 60|0.40000001|0",
"SolNode88":"목성|Adrastea|Extermination|Corpus|9 - 10|20 - 60|0.40000001|0",
"? - 41":"목성||Assassination|Grineer|1 - 1|20 - 60|0.40000001|0",
"SolNode97":"목성|Amalthea|Sabotage|Corpus|8 - 9|20 - 60|0.40000001|0",
"SolNode126":"목성|Metis|Capture|Corpus|9 - 10|20 - 60|0.40000001|0",
"? - 42":"목성||Assassination|Grineer|1 - 1|20 - 60|0.40000001|0",
"SolNode125":"목성|Io|Defense|Corpus|8 - 11|20 - 60|0.40000001|0",
"SolNode100":"목성|Elara|Survival|Corpus|10 - 15|20 - 60|0.40000001|0",
"SolNode10":"목성|Thebe|Deception|Corpus|8 - 9|20 - 60|0.40000001|0",
"PvpNode8":"목성|Conclave|MT_PVP|Corpus|200 - 300|20 - 60|0.40000001|1",
"SolNode25":"목성|Callisto|Interception|Corpus|9 - 12|20 - 60|0.40000001|1",
"SolNode121":"목성|Carpo|Extermination|Corpus|9 - 10|20 - 60|0.40000001|1",
"SolNode53":"목성|Themisto|Assassination|Corpus|10 - 11|20 - 60|0.40000001|1",
"? - 43":"목성||Assassination|Grineer|1 - 1|20 - 60|0.40000001|1",
"SolNode74":"목성|Carme|Mobile Defense|Corpus|10 - 11|20 - 60|0.40000001|1",
"ClanNode4":"목성|Sinai|Defense|Infestation|13 - 23|20 - 60|0.40000001|1",
"EventNode4":"목성|Bres|Sabotage|Corpus|8 - 8|20 - 60|0.40000001|1",
"SolNode73":"목성|Ananke|Capture|Corpus|10 - 11|20 - 60|0.40000001|1",
"? - 44":"목성||Assassination|Grineer|1 - 1|20 - 60|0.40000001|2",
"? - 45":"목성||Assassination|Grineer|1 - 1|20 - 60|0.40000001|2",
"? - 46":"목성||Assassination|Grineer|1 - 1|20 - 60|0.40000001|2",
"? - 47":"목성||Assassination|Grineer|1 - 1|20 - 60|0.40000001|2",
"? - 48":"목성||Assassination|Grineer|1 - 1|20 - 60|0.40000001|2",
"? - 49":"목성||Assassination|Grineer|1 - 1|20 - 60|0.40000001|2",
"ClanNode5":"목성|Cameria|Survival|Infestation|13 - 23|20 - 60|0.40000001|2",
"? - 50":"목성||Assassination|Grineer|1 - 1|20 - 60|0.40000001|2",
"? - 51":"목성||Assassination|Grineer|1 - 1|20 - 60|0.40000001|2",
"SolNode110":"토성|Hyperion|Extermination|Grineer|11 - 12|30 - 60|0.5|0",
"SolNode7":"토성|Epimetheus|Deception|Grineer|10 - 11|30 - 60|0.5|0",
"? - 52":"토성||Assassination|Grineer|1 - 1|30 - 60|0.5|0",
"SolNode42":"토성|Helene|Defense|Grineer|12 - 17|30 - 60|0.5|0",
"? - 53":"토성||Assassination|Grineer|1 - 1|30 - 60|0.5|0",
"SolNode19":"토성|Enceladus|Capture|Grineer|10 - 11|30 - 60|0.5|0",
"SolNode96":"토성|Titan|Sabotage|Grineer|12 - 13|30 - 60|0.5|0",
"? - 54":"토성||Assassination|Grineer|1 - 1|30 - 60|0.5|0",
"SolNode67":"토성|Dione|Sabotage|Grineer|9 - 10|30 - 60|0.5|0",
"? - 55":"토성||Assassination|Grineer|1 - 1|30 - 60|0.5|1",
"SolNode44":"토성|Mimas|Survival|Grineer|11 - 16|30 - 60|0.5|1",
"SolNode91":"토성|Iapetus|Interception|Grineer|11 - 12|30 - 60|0.5|1",
"SolNode47":"토성|Janus|Extermination|Grineer|10 - 11|30 - 60|0.5|1",
"SolNode93":"토성|Keeler|Survival|Grineer|11 - 16|30 - 60|0.5|1",
"SolNode32":"토성|Tethys|Assassination|Grineer|11 - 12|30 - 60|0.5|1",
"? - 56":"토성||Assassination|Grineer|1 - 1|30 - 60|0.5|1",
"SolNode80":"토성|Phoebe|Capture|Grineer|9 - 10|30 - 60|0.5|1",
"SolNode18":"토성|Rhea|Sabotage|Grineer|10 - 11|30 - 60|0.5|1",
"? - 57":"토성||Assassination|Grineer|1 - 1|30 - 60|0.5|2",
"SolNode37":"토성|Pallene|Sabotage|Grineer|11 - 12|30 - 60|0.5|2",
"SolNode20":"토성|Telesto|Extermination|Grineer|12 - 13|30 - 60|0.5|2",
"SolNode86":"토성|Aegaeon|Extermination|Grineer|11 - 12|30 - 60|0.5|2",
"SolNode55":"토성|Methone|Deception|Grineer|11 - 12|30 - 60|0.5|2",
"SolNode70":"토성|Cassini|Survival|Grineer|9 - 14|30 - 60|0.5|2",
"SolNode31":"토성|Anthe|Rescue|Grineer|11 - 12|30 - 60|0.5|2",
"? - 58":"토성||Assassination|Grineer|1 - 1|30 - 60|0.5|2",
"SolNode50":"토성|Numa|Rescue|Grineer|10 - 11|30 - 60|0.5|2",
"? - 59":"토성||Assassination|Grineer|1 - 1|30 - 60|0.5|3",
"SolNode82":"토성|Calypso|Capture|Grineer|12 - 13|30 - 60|0.5|3",
"? - 60":"토성||Assassination|Grineer|1 - 1|30 - 60|0.5|3",
"? - 61":"토성||Assassination|Grineer|1 - 1|30 - 60|0.5|3",
"EventNode5":"토성|Birog|Defense|Grineer|9 - 9|30 - 60|0.5|3",
"PvpNode0":"토성|Conclave|MT_PVP|Grineer|50 - 150|30 - 60|0.5|3",
"ClanNode13":"토성|Piscinas|Survival|Infestation|14 - 24|30 - 60|0.5|3",
"? - 62":"토성||Assassination|Grineer|1 - 1|30 - 60|0.5|3",
"ClanNode12":"토성|Caracol|Defense|Infestation|14 - 24|30 - 60|0.5|3",
"SolNode29":"천왕성|Oberon|Extermination|Grineer|16 - 17|30 - 70|0.40000001|0",
"SolNode33":"천왕성|Ariel|Sabotage|Grineer|16 - 17|30 - 70|0.40000001|0",
"? - 63":"천왕성||Assassination|Grineer|1 - 1|30 - 70|0.40000001|0",
"SolNode105":"천왕성|Titania|Assassination|Grineer|19 - 20|30 - 70|0.40000001|0",
"SolNode64":"천왕성|Umbriel|Spy|Grineer|16 - 17|30 - 70|0.40000001|0",
"SolNode3":"천왕성|Cordelia|Extermination|Grineer|17 - 18|30 - 70|0.40000001|0",
"? - 64":"천왕성||Assassination|Grineer|1 - 1|30 - 70|0.40000001|0",
"SolNode90":"천왕성|Miranda|Defense|Grineer|17 - 22|30 - 70|0.40000001|0",
"SolNode69":"천왕성|Ophelia|Survival|Grineer|18 - 23|30 - 70|0.40000001|0",
"SolNode52":"천왕성|Portia|Sabotage|Grineer|16 - 17|30 - 70|0.40000001|1",
"SolNode83":"천왕성|Cressida|Survival|Grineer|16 - 17|30 - 70|0.40000001|1",
"SolNode111":"천왕성|Juliet|Deception|Grineer|18 - 19|30 - 70|0.40000001|1",
"SolNode98":"천왕성|Desdemona|Capture|Grineer|17 - 18|30 - 70|0.40000001|1",
"SolNode77":"천왕성|Cupid|Survival|Grineer|18 - 23|30 - 70|0.40000001|1",
"SolNode9":"천왕성|Rosalind|Spy|Grineer|18 - 19|30 - 70|0.40000001|1",
"? - 65":"천왕성||Assassination|Grineer|1 - 1|30 - 70|0.40000001|1",
"SolNode13":"천왕성|Bianca|Defense|Grineer|16 - 21|30 - 70|0.40000001|1",
"? - 66":"천왕성||Assassination|Grineer|1 - 1|30 - 70|0.40000001|1",
"? - 67":"천왕성||Assassination|Grineer|1 - 1|30 - 70|0.40000001|2",
"SolNode40":"천왕성|Prospero|Sabotage|Grineer|17 - 18|30 - 70|0.40000001|2",
"SolNode5":"천왕성|Perdita|Deception|Grineer|18 - 19|30 - 70|0.40000001|2",
"SolNode116":"천왕성|Mab|Rescue|Grineer|15 - 16|30 - 70|0.40000001|2",
"SolNode112":"천왕성|Setebos|Sabotage|Grineer|18 - 19|30 - 70|0.40000001|2",
"SolNode60":"천왕성|Caliban|Rescue|Grineer|17 - 18|30 - 70|0.40000001|2",
"? - 68":"천왕성||Assassination|Grineer|1 - 1|30 - 70|0.40000001|2",
"SolNode114":"천왕성|Puck|Extermination|Grineer|17 - 18|30 - 70|0.40000001|2",
"? - 69":"천왕성||Assassination|Grineer|1 - 1|30 - 70|0.40000001|2",
"? - 70":"천왕성||Assassination|Grineer|1 - 1|30 - 70|0.40000001|3",
"SolNode34":"천왕성|Sycorax|Extermination|Grineer|17 - 18|30 - 70|0.40000001|3",
"SolNode122":"천왕성|Stephano|Interception|Grineer|18 - 23|30 - 70|0.40000001|3",
"SolNode124":"천왕성|Trinculo|Capture|Grineer|15 - 16|30 - 70|0.40000001|3",
"? - 71":"천왕성||Assassination|Grineer|1 - 1|30 - 70|0.40000001|3",
"? - 72":"천왕성||Assassination|Grineer|1 - 1|30 - 70|0.40000001|3",
"EventNode6":"천왕성|Ethniu|Survival|Grineer|15 - 15|30 - 70|0.40000001|3",
"ClanNode17":"천왕성|Assur|Survival|Infestation|20 - 30|30 - 70|0.40000001|3",
"ClanNode16":"천왕성|Ur|Defense|Infestation|20 - 30|30 - 70|0.40000001|3",
"SolNode49":"해왕성|Larissa|Mobile Defense|Corpus|20 - 21|30 - 70|0.5|0",
"SolNode95":"해왕성|Thalassa|Rescue|Corpus|20 - 25|30 - 70|0.5|0",
"SolNode117":"해왕성|Naiad|Deception|Corpus|20 - 21|30 - 70|0.5|0",
"SolNode1":"해왕성|Galatea|Capture|Corpus|22 - 23|30 - 70|0.5|0",
"? - 73":"해왕성||Assassination|Grineer|1 - 1|30 - 70|0.5|0",
"? - 74":"해왕성||Assassination|Grineer|1 - 1|30 - 70|0.5|0",
"SolNode17":"해왕성|Proteus|Defense|Corpus|22 - 24|30 - 70|0.5|0",
"SolNode78":"해왕성|Triton|Survival|Corpus|23 - 28|30 - 70|0.5|0",
"SolNode6":"해왕성|Despina|Defense|Corpus|23 - 28|30 - 70|0.5|0",
"SolNode57":"해왕성|Sao|Deception|Corpus|21 - 22|30 - 70|0.5|1",
"SolNode120":"해왕성|Halimede|Sabotage|Corpus|21 - 22|30 - 70|0.5|1",
"? - 75":"해왕성||Assassination|Grineer|1 - 1|30 - 70|0.5|1",
"SolNode62":"해왕성|Neso|Extermination|Corpus|21 - 22|30 - 70|0.5|1",
"? - 76":"해왕성||Assassination|Grineer|1 - 1|30 - 70|0.5|1",
"SolNode127":"해왕성|Psamathe|Assassination|Corpus|22 - 23|30 - 70|0.5|1",
"SolNode118":"해왕성|Laomedeia|Spy|Corpus|22 - 23|30 - 70|0.5|1",
"? - 77":"해왕성||Assassination|Grineer|1 - 1|30 - 70|0.5|1",
"SolNode84":"해왕성|Nereid|Rescue|Corpus|22 - 23|30 - 70|0.5|1",
"ClanNode20":"해왕성|Yursa|Defense|Infestation|25 - 35|30 - 70|0.5|2",
"ClanNode21":"해왕성|Kelashin|Survival|Infestation|25 - 35|30 - 70|0.5|2",
"? - 78":"해왕성||Assassination|Grineer|1 - 1|30 - 70|0.5|2",
"? - 79":"해왕성||Assassination|Grineer|1 - 1|30 - 70|0.5|2",
"EventNode7":"해왕성|Buarainech|Sabotage|Corpus|20 - 20|30 - 70|0.5|2",
"PvpNode3":"해왕성|Conclave|MT_PVP|Corpus|150 - 300|30 - 70|0.5|2",
"? - 80":"해왕성||Assassination|Grineer|1 - 1|30 - 70|0.5|2",
"? - 81":"해왕성||Assassination|Grineer|1 - 1|30 - 70|0.5|2",
"? - 82":"해왕성||Assassination|Grineer|1 - 1|30 - 70|0.5|2",
"SolNode4":"명왕성|Acheron|Extermination|Corpus|25 - 26|30 - 75|0.5|0",
"SolNode72":"명왕성|Outer Terminus|Defense|Corpus|28 - 33|30 - 75|0.5|0",
"? - 83":"명왕성||Assassination|Grineer|1 - 1|30 - 75|0.5|0",
"SolNode48":"명왕성|Regna|Rescue|Corpus|27 - 28|30 - 75|0.5|0",
"SolNode21":"명왕성|Narcissus|Defense|Corpus|26 - 31|30 - 75|0.5|0",
"SolNode92":"명왕성|Charon|Sabotage|Corpus|27 - 28|30 - 75|0.5|0",
"SolNode76":"명왕성|Hydra|Capture|Corpus|26 - 27|30 - 75|0.5|0",
"SolNode51":"명왕성|Hades|Assassination|Corpus|28 - 29|30 - 75|0.5|0",
"SolNode38":"명왕성|Minthe|Mobile Defense|Corpus|26 - 27|30 - 75|0.5|0",
"? - 84":"명왕성||Assassination|Grineer|1 - 1|30 - 75|0.5|1",
"SolNode8":"명왕성|Nix|Deception|Corpus|25 - 26|30 - 75|0.5|1",
"SolNode56":"명왕성|Cypress|Sabotage|Corpus|27 - 28|30 - 75|0.5|1",
"SolNode43":"명왕성|Cerberus|Interception|Corpus|27 - 28|30 - 75|0.5|1",
"SolNode81":"명왕성|Palus|Survival|Corpus|27 - 32|30 - 75|0.5|1",
"ClanNode24":"명왕성|Sechura|Defense|Infestation|30 - 40|30 - 75|0.5|1",
"? - 85":"명왕성||Assassination|Grineer|1 - 1|30 - 75|0.5|1",
"SolNode102":"명왕성|Oceanum|Spy|Corpus|27 - 28|30 - 75|0.5|1",
"PvpNode6":"명왕성|Conclave|MT_PVP|Corpus|1000 - 1500|30 - 75|0.5|1",
"? - 86":"명왕성||Assassination|Grineer|1 - 1|30 - 75|0.5|2",
"ClanNode25":"명왕성|Hieracon|Survival|Infestation|30 - 40|30 - 75|0.5|2",
"? - 87":"명왕성||Assassination|Grineer|1 - 1|30 - 75|0.5|2",
"? - 88":"명왕성||Assassination|Grineer|1 - 1|30 - 75|0.5|2",
"? - 89":"명왕성||Assassination|Grineer|1 - 1|30 - 75|0.5|2",
"EventNode8":"명왕성|Corb|Capture|Corpus|25 - 25|30 - 75|0.5|2",
"? - 90":"명왕성||Assassination|Grineer|1 - 1|30 - 75|0.5|2",
"? - 91":"명왕성||Assassination|Grineer|1 - 1|30 - 75|0.5|2",
"? - 92":"명왕성||Assassination|Grineer|1 - 1|30 - 75|0.5|2",
"SolNode136":"세레스|Olla|Rescue|Grineer|21 - 22|30 - 70|0.5|0",
"? - 93":"세레스||Assassination|Grineer|1 - 1|30 - 70|0.5|0",
"SolNode131":"세레스|Pallas|Sabotage|Grineer|20 - 21|30 - 70|0.5|0",
"SolNode133":"세레스|Vedic|Extermination|Grineer|20 - 21|30 - 70|0.5|0",
"SolNode135":"세레스|Thon|Sabotage|Grineer|21 - 22|30 - 70|0.5|0",
"? - 94":"세레스||Assassination|Grineer|1 - 1|30 - 70|0.5|0",
"? - 95":"세레스||Assassination|Grineer|1 - 1|30 - 70|0.5|0",
"SolNode132":"세레스|Bode|Capture|Grineer|20 - 21|30 - 70|0.5|0",
"SolNode134":"세레스|Varro|Defense|Grineer|20 - 25|30 - 70|0.5|0",
"SolNode139":"세레스|Lex|Spy|Grineer|22 - 23|30 - 70|0.5|1",
"SolNode141":"세레스|Ker|Deception|Grineer|22 - 23|30 - 70|0.5|1",
"SolNode137":"세레스|Nuovo|Survival|Grineer|20 - 25|30 - 70|0.5|1",
"SolNode142":"세레스|Hapke|Capture|Grineer|22 - 23|30 - 70|0.5|1",
"SolNode140":"세레스|Kiste|Mobile Defense|Grineer|22 - 23|30 - 70|0.5|1",
"? - 96":"세레스||Assassination|Grineer|1 - 1|30 - 70|0.5|1",
"SolNode138":"세레스|Ludi|Extermination|Grineer|21 - 22|30 - 70|0.5|1",
"SolNode143":"세레스|Gefion|MT_RETRIEVAL|Grineer|23 - 24|30 - 70|0.5|1",
"SolNode144":"세레스|Exta|Assassination|Grineer|24 - 25|30 - 70|0.5|1",
"SolNode149":"세레스|Casta|Defense|Grineer|24 - 29|30 - 70|0.5|2",
"? - 97":"세레스||Assassination|Grineer|1 - 1|30 - 70|0.5|2",
"? - 98":"세레스||Assassination|Grineer|1 - 1|30 - 70|0.5|2",
"SolNode148":"세레스|Cerium|MT_RETRIEVAL|Grineer|23 - 24|30 - 70|0.5|2",
"SolNode147":"세레스|Cinxia|Rescue|Grineer|23 - 24|30 - 70|0.5|2",
"SolNode150":"세레스|Albedo|Deception|Grineer|21 - 22|30 - 70|0.5|2",
"SolNode145":"세레스|Egeria|Survival|Grineer|22 - 27|30 - 70|0.5|2",
"? - 99":"세레스||Assassination|Grineer|1 - 1|30 - 70|0.5|2",
"SolNode146":"세레스|Draco|Interception|Grineer|23 - 24|30 - 70|0.5|2",
"? - 100":"세레스||Assassination|Grineer|1 - 1|30 - 70|0.5|3",
"? - 101":"세레스||Assassination|Grineer|1 - 1|30 - 70|0.5|3",
"? - 102":"세레스||Assassination|Grineer|1 - 1|30 - 70|0.5|3",
"? - 103":"세레스||Assassination|Grineer|1 - 1|30 - 70|0.5|3",
"EventNode9":"세레스|Conand|Sabotage|Grineer|20 - 20|30 - 70|0.5|3",
"? - 104":"세레스||Assassination|Grineer|1 - 1|30 - 70|0.5|3",
"? - 105":"세레스||Assassination|Grineer|1 - 1|30 - 70|0.5|3",
"ClanNode23":"세레스|Gabii|Survival|Infestation|25 - 35|30 - 70|0.5|3",
"ClanNode22":"세레스|Seimeni|Defense|Infestation|25 - 35|30 - 70|0.5|3",
"SolNode156":"에리스|Cyath|Mobile Defense|Infestation|19 - 20|30 - 70|0.40000001|0",
"SolNode155":"에리스|Cosis|Capture|Infestation|18 - 19|30 - 70|0.40000001|0",
"SolNode154":"에리스|Candiru|Hive Sabotage|Infestation|19 - 20|30 - 70|0.40000001|0",
"SolNode152":"에리스|Ascar|Mobile Defense|Infestation|18 - 19|30 - 70|0.40000001|0",
"? - 106":"에리스||Assassination|Grineer|1 - 1|30 - 70|0.40000001|0",
"SolNode157":"에리스|Giardia|Mobile Defense|Infestation|19 - 20|30 - 70|0.40000001|0",
"? - 107":"에리스||Assassination|Grineer|1 - 1|30 - 70|0.40000001|0",
"SolNode151":"에리스|Acanth|Extermination|Infestation|18 - 19|30 - 70|0.40000001|0",
"SolNode153":"에리스|Brugia|Rescue|Infestation|18 - 19|30 - 70|0.40000001|0",
"SolNode159":"에리스|Lepis|Hive Sabotage|Infestation|20 - 21|30 - 70|0.40000001|1",
"SolNode164":"에리스|Kala-azar|Defense|Infestation|21 - 26|30 - 70|0.40000001|1",
"SolNode161":"에리스|Hymeno|Survival|Infestation|21 - 26|30 - 70|0.40000001|1",
"SolNode162":"에리스|Isos|Capture|Infestation|21 - 22|30 - 70|0.40000001|1",
"? - 108":"에리스||Assassination|Grineer|1 - 1|30 - 70|0.40000001|1",
"SolNode158":"에리스|Gnathos|Defense|Infestation|20 - 25|30 - 70|0.40000001|1",
"SolNode160":"에리스|Histo|Extermination|Infestation|20 - 21|30 - 70|0.40000001|1",
"SolNode165":"에리스|Naeglar|Extermination|Infestation|22 - 23|30 - 70|0.40000001|1",
"SolNode163":"에리스|Ixodes|Defense|Infestation|20 - 25|30 - 70|0.40000001|1",
"? - 109":"에리스||Assassination|Grineer|1 - 1|30 - 70|0.40000001|2",
"SolNode171":"에리스|Saxis|Extermination|Infestation|20 - 21|30 - 70|0.40000001|2",
"SolNode168":"에리스|Phalan|Survival|Infestation|18 - 23|30 - 70|0.40000001|2",
"? - 110":"에리스||Assassination|Grineer|1 - 1|30 - 70|0.40000001|2",
"SolNode167":"에리스|Oestrus|Mobile Defense|Infestation|19 - 20|30 - 70|0.40000001|2",
"SolNode170":"에리스|Ranova|Rescue|Infestation|20 - 21|30 - 70|0.40000001|2",
"SolNode169":"에리스|Psoro|Hive Sabotage|Infestation|19 - 20|30 - 70|0.40000001|2",
"SolNode166":"에리스|Nimus|Survival|Infestation|21 - 22|30 - 70|0.40000001|2",
"? - 111":"에리스||Assassination|Grineer|1 - 1|30 - 70|0.40000001|2",
"EventNode10":"에리스|Lugh|Deception|Corpus|18 - 18|30 - 70|0.40000001|3",
"SolNode173":"에리스|Solium|Mobile Defense|Infestation|19 - 20|30 - 70|0.40000001|3",
"ClanNode18":"에리스|Akkad|Defense|Infestation|23 - 33|30 - 70|0.40000001|3",
"SolNode174":"에리스|Sparga|Rescue|Infestation|19 - 20|30 - 70|0.40000001|3",
"SolNode172":"에리스|Xini|Defense|Infestation|19 - 24|30 - 70|0.40000001|3",
"SolNode176":"에리스|Viver|Interception|Corpus|20 - 21|30 - 70|0.40000001|3",
"ClanNode19":"에리스|Zabala|Survival|Infestation|23 - 33|30 - 70|0.40000001|3",
"SolNode175":"에리스|Sporid|Hive Sabotage|Infestation|20 - 21|30 - 70|0.40000001|3",
"PvpNode4":"에리스|Conclave|MT_PVP|Corpus|350 - 500|30 - 70|0.40000001|3",
"SolNode177":"세드나|Kappa|Mobile Defense|Grineer|12 - 13|30 - 80|0.5|0",
"SolNode184":"세드나|Rusalka|Deception|Grineer|13 - 14|30 - 80|0.5|0",
"SolNode182":"세드나|Camenae|Defense|Grineer|13 - 18|30 - 80|0.5|0",
"SolNode181":"세드나|Adaro|Extermination|Grineer|13 - 14|30 - 80|0.5|0",
"SolNode183":"세드나|Vodyanoi|Mobile Defense|Grineer|14 - 15|30 - 80|0.5|0",
"SolNode178":"세드나|Hyosube|Sabotage|Grineer|12 - 13|30 - 80|0.5|0",
"SolNode180":"세드나|Undine|Sabotage|Grineer|12 - 13|30 - 80|0.5|0",
"SolNode179":"세드나|Jengu|Rescue|Grineer|12 - 13|30 - 80|0.5|0",
"? - 112":"세드나||Assassination|Grineer|1 - 1|30 - 80|0.5|0",
"SolNode190":"세드나|Nakki|Sabotage|Grineer|13 - 14|30 - 80|0.5|1",
"SolNode185":"세드나|Berehynia|Interception|Grineer|13 - 18|30 - 80|0.5|1",
"SolNode192":"세드나|Tikoloshe|Spy|Grineer|14 - 15|30 - 80|0.5|1",
"? - 113":"세드나||Assassination|Grineer|1 - 1|30 - 80|0.5|1",
"SolNode187":"세드나|Selkie|Survival|Grineer|13 - 18|30 - 80|0.5|1",
"SolNode191":"세드나|Marid|Extermination|Grineer|14 - 15|30 - 80|0.5|1",
"SolNode186":"세드나|Phithale|Sabotage|Grineer|13 - 14|30 - 80|0.5|1",
"SolNode188":"세드나|Kelpie|Sabotage|Grineer|12 - 13|30 - 80|0.5|1",
"SolNode189":"세드나|Naga|Rescue|Grineer|12 - 13|30 - 80|0.5|1",
"? - 114":"세드나||Assassination|Grineer|1 - 1|30 - 80|0.5|2",
"? - 115":"세드나||Assassination|Grineer|1 - 1|30 - 80|0.5|2",
"SolNode199":"세드나|Yam|Sabotage|Grineer|14 - 15|30 - 80|0.5|2",
"SolNode194":"세드나|Ponaturi|Deception|Grineer|12 - 13|30 - 80|0.5|2",
"SolNode193":"세드나|Merrow|Assassination|Grineer|14 - 15|30 - 80|0.5|2",
"SolNode196":"세드나|Charybdis|Deception|Grineer|13 - 14|30 - 80|0.5|2",
"SolNode197":"세드나|Graeae|Mobile Defense|Grineer|13 - 14|30 - 80|0.5|2",
"SolNode195":"세드나|Hydron|Defense|Grineer|13 - 18|30 - 80|0.5|2",
"SolNode198":"세드나|Scylla|Spy|Grineer|13 - 14|30 - 80|0.5|2",
"EventNode11":"세드나|Nemed|Spy|Grineer|12 - 12|30 - 80|0.5|3",
"? - 116":"세드나||Assassination|Grineer|1 - 1|30 - 80|0.5|3",
"SolNode201":"세드나|Tiamat|Capture|Grineer|12 - 13|30 - 80|0.5|3",
"SolNode202":"세드나|Yemaja|Survival|Grineer|14 - 19|30 - 80|0.5|3",
"PvpNode7":"세드나|Conclave|MT_PVP|Grineer|300 - 700|30 - 80|0.5|3",
"? - 117":"세드나||Assassination|Grineer|1 - 1|30 - 80|0.5|3",
"ClanNode14":"세드나|Amarna|Survival|Infestation|17 - 27|30 - 80|0.5|3",
"SolNode200":"세드나|Veles|Rescue|Grineer|14 - 15|30 - 80|0.5|3",
"ClanNode15":"세드나|Sangeru|Defense|Infestation|17 - 27|30 - 80|0.5|3",
"SolNode203":"유로파|Abaddon|Capture|Corpus|12 - 13|10 - 75|0.40000001|0",
"SolNode207":"유로파|Gamygyn|Spy|Corpus|14 - 15|10 - 75|0.40000001|0",
"SolNode204":"유로파|Armaros|Interception|Corpus|14 - 15|10 - 75|0.40000001|0",
"SolNode209":"유로파|Morax|Spy|Corpus|13 - 14|10 - 75|0.40000001|0",
"SolNode206":"유로파|Eligor|Defense|Corpus|12 - 17|10 - 75|0.40000001|0",
"SolNode208":"유로파|Lillith|Survival|Corpus|14 - 19|10 - 75|0.40000001|0",
"SolNode210":"유로파|Naamah|Assassination|Corpus|15 - 16|10 - 75|0.40000001|0",
"? - 118":"유로파||Assassination|Grineer|1 - 1|10 - 75|0.40000001|0",
"SolNode205":"유로파|Baal|Mobile Defense|Corpus|13 - 14|10 - 75|0.40000001|0",
"? - 119":"유로파||Assassination|Grineer|1 - 1|10 - 75|0.40000001|1",
"SolNode216":"유로파|Valefor|Defense|Corpus|13 - 18|10 - 75|0.40000001|1",
"? - 120":"유로파||Assassination|Grineer|1 - 1|10 - 75|0.40000001|1",
"? - 121":"유로파||Assassination|Grineer|1 - 1|10 - 75|0.40000001|1",
"SolNode214":"유로파|Sorath|Sabotage|Corpus|13 - 14|10 - 75|0.40000001|1",
"SolNode211":"유로파|Ose|Survival|Corpus|14 - 19|10 - 75|0.40000001|1",
"SolNode215":"유로파|Valac|Deception|Corpus|14 - 15|10 - 75|0.40000001|1",
"SolNode213":"유로파|Shax|Rescue|Corpus|14 - 15|10 - 75|0.40000001|1",
"SolNode212":"유로파|Paimon|Defense|Corpus|15 - 20|10 - 75|0.40000001|1",
"PvpNode5":"유로파|Conclave|MT_PVP|Corpus|500 - 1000|10 - 75|0.40000001|2",
"SolNode217":"유로파|Orias|Rescue|Corpus|13 - 14|10 - 75|0.40000001|2",
"SolNode218":"유로파|Zagan|Capture|Corpus|14 - 15|10 - 75|0.40000001|2",
"ClanNode6":"유로파|Larzac|Defense|Infestation|17 - 27|10 - 75|0.40000001|2",
"? - 122":"유로파||Assassination|Grineer|1 - 1|10 - 75|0.40000001|2",
"SolNode219":"유로파|Beleth|Capture|Corpus|13 - 14|10 - 75|0.40000001|2",
"SolNode220":"유로파|Kokabiel|Sabotage|Corpus|14 - 15|10 - 75|0.40000001|2",
"EventNode12":"유로파|Neit|Capture|Corpus|12 - 12|10 - 75|0.40000001|2",
"? - 123":"유로파||Assassination|Grineer|1 - 1|10 - 75|0.40000001|2",
"? - 124":"유로파||Assassination|Grineer|1 - 1|10 - 75|0.40000001|3",
"? - 125":"유로파||Assassination|Grineer|1 - 1|10 - 75|0.40000001|3",
"? - 126":"유로파||Assassination|Grineer|1 - 1|10 - 75|0.40000001|3",
"? - 127":"유로파||Assassination|Grineer|1 - 1|10 - 75|0.40000001|3",
"? - 128":"유로파||Assassination|Grineer|1 - 1|10 - 75|0.40000001|3",
"? - 129":"유로파||Assassination|Grineer|1 - 1|10 - 75|0.40000001|3",
"ClanNode7":"유로파|Cholistan|Survival|Infestation|17 - 27|10 - 75|0.40000001|3",
"? - 130":"유로파||Assassination|Grineer|1 - 1|10 - 75|0.40000001|3",
"? - 131":"유로파||Assassination|Grineer|1 - 1|10 - 75|0.40000001|3",
"SettlementNode6":"Phobos|Limtoc|Capture|Grineer|14 - 15|20 - 50|0.30000001|0",
"PvpNode2":"Phobos|Conclave|MT_PVP|Corrupted|500 - 700|20 - 50|0.30000001|0",
"SettlementNode1":"Phobos|Roche|Extermination|Grineer|13 - 14|20 - 50|0.30000001|0",
"? - 132":"Phobos||Assassination|Grineer|1 - 1|20 - 50|0.30000001|0",
"SettlementNode7":"Phobos|Hall|Mobile Defense|Grineer|14 - 15|20 - 50|0.30000001|0",
"SettlementNode5":"Phobos|Grildrig|Rescue|Grineer|13 - 14|20 - 50|0.30000001|0",
"SettlementNode3":"Phobos|Stickney|Survival|Grineer|13 - 18|20 - 50|0.30000001|0",
"SettlementNode2":"Phobos|Skyresh|Deception|Grineer|13 - 14|20 - 50|0.30000001|0",
"SettlementNode4":"Phobos|Drunlo|Defense|Grineer|13 - 18|20 - 50|0.30000001|0",
"SettlementNode13":"Phobos|D'Arrest|Sabotage|Grineer|16 - 17|20 - 50|0.30000001|1",
"SettlementNode12":"Phobos|Monolith|Rescue|Grineer|15 - 16|20 - 50|0.30000001|1",
"SettlementNode10":"Phobos|Kepler|Defense|Grineer|15 - 20|20 - 50|0.30000001|1",
"SettlementNode15":"Phobos|Sharpless|Mobile Defense|Grineer|16 - 17|20 - 50|0.30000001|1",
"? - 133":"Phobos||Assassination|Grineer|1 - 1|20 - 50|0.30000001|1",
"SettlementNode8":"Phobos|Reldresal|Sabotage|Grineer|14 - 15|20 - 50|0.30000001|1",
"SettlementNode11":"Phobos|Gulliver|Rescue|Grineer|15 - 16|20 - 50|0.30000001|1",
"SettlementNode14":"Phobos|Shklovsky|Spy|Grineer|16 - 17|20 - 50|0.30000001|1",
"SettlementNode9":"Phobos|Clustril|Extermination|Grineer|15 - 16|20 - 50|0.30000001|1",
"SettlementNode16":"Phobos|Wendell|Survival|Grineer|16 - 21|20 - 50|0.30000001|2",
"SettlementNode19":"Phobos|Todd|Capture|Grineer|16 - 17|20 - 50|0.30000001|2",
"? - 134":"Phobos||Assassination|Grineer|1 - 1|20 - 50|0.30000001|2",
"SettlementNode17":"Phobos|Flimnap|Deception|Grineer|16 - 17|20 - 50|0.30000001|2",
"ClanNode10":"Phobos|Memphis|Defense|Infestation|18 - 28|20 - 50|0.30000001|2",
"SettlementNode20":"Phobos|Iliad|Assassination|Grineer|17 - 18|20 - 50|0.30000001|2",
"? - 135":"Phobos||Assassination|Grineer|1 - 1|20 - 50|0.30000001|2",
"? - 136":"Phobos||Assassination|Grineer|1 - 1|20 - 50|0.30000001|2",
"SettlementNode18":"Phobos|Opik|Interception|Grineer|16 - 17|20 - 50|0.30000001|2",
"? - 137":"Phobos||Assassination|Grineer|1 - 1|20 - 50|0.30000001|3",
"? - 138":"Phobos||Assassination|Grineer|1 - 1|20 - 50|0.30000001|3",
"? - 139":"Phobos||Assassination|Grineer|1 - 1|20 - 50|0.30000001|3",
"? - 140":"Phobos||Assassination|Grineer|1 - 1|20 - 50|0.30000001|3",
"? - 141":"Phobos||Assassination|Grineer|1 - 1|20 - 50|0.30000001|3",
"? - 142":"Phobos||Assassination|Grineer|1 - 1|20 - 50|0.30000001|3",
"? - 143":"Phobos||Assassination|Grineer|1 - 1|20 - 50|0.30000001|3",
"? - 144":"Phobos||Assassination|Grineer|1 - 1|20 - 50|0.30000001|3",
"ClanNode11":"Phobos|Zeugma|Survival|Infestation|18 - 28|20 - 50|0.30000001|3"}